[
    {
        "id": 274019561,
        "name": "Kongde Ri",
        "ele": "6187",
        "realCoord": {
            "lat": 27.8019697,
            "lon": 86.6149573
        },
        "group": 1566,
        "estimatedCoord": {
            "lat": 27.802500000000002,
            "lon": 86.61625
        },
        "distance": 140.2004103208352
    },
    {
        "id": 274028194,
        "name": "Thamserku",
        "ele": "6623",
        "realCoord": {
            "lat": 27.7898577,
            "lon": 86.785298
        },
        "group": 1950,
        "estimatedCoord": {
            "lat": 27.79007246376811,
            "lon": 86.78641304347825
        },
        "distance": 112.29157391548542
    },
    {
        "id": 274029669,
        "name": "Kusum Kangguru",
        "ele": "6367",
        "realCoord": {
            "lat": 27.7322274,
            "lon": 86.791863
        },
        "group": 1963,
        "estimatedCoord": {
            "lat": 27.731057692307694,
            "lon": 86.78919871794872
        },
        "distance": 292.8024344285429
    },
    {
        "id": 288180659,
        "name": "चोयु ཇོ་བོ་དབུ་ཡ 卓奧有山 Cho Oyu",
        "ele": "8201",
        "realCoord": {
            "lat": 28.0941964,
            "lon": 86.6608234
        },
        "group": 4038,
        "estimatedCoord": {
            "lat": 28.094459459459465,
            "lon": 86.66081081081079
        },
        "distance": 29.28612419204462
    },
    {
        "id": 288181001,
        "name": "ग्याचुङ काङ 格重康峰 Gyachung Kang",
        "ele": "7952",
        "realCoord": {
            "lat": 28.0980314,
            "lon": 86.7448435
        },
        "group": 4260,
        "estimatedCoord": {
            "lat": 28.098106060606053,
            "lon": 86.74458333333332
        },
        "distance": 26.84452118027488
    },
    {
        "id": 335376854,
        "name": "ल्होत्से ལྷོ་རྩེ 洛子峰 Lhotse",
        "ele": "8516",
        "realCoord": {
            "lat": 27.9616389,
            "lon": 86.9326734
        },
        "group": 2308,
        "estimatedCoord": {
            "lat": 27.96193333333333,
            "lon": 86.93353333333333
        },
        "distance": 90.60964331898924
    },
    {
        "id": 425189343,
        "name": "Gokyo Ri",
        "ele": "5360",
        "realCoord": {
            "lat": 27.9614256,
            "lon": 86.6830869
        },
        "group": 1737,
        "estimatedCoord": {
            "lat": 27.961287878787882,
            "lon": 86.68295454545455
        },
        "distance": 20.093440655456565
    },
    {
        "id": 442260815,
        "name": "Machhermo Peak",
        "ele": "6017",
        "realCoord": {
            "lat": 27.9289461,
            "lon": 86.6803363
        },
        "group": 1727,
        "estimatedCoord": {
            "lat": 27.928837719298247,
            "lon": 86.68098684210527
        },
        "distance": 65.05857429396512
    },
    {
        "id": 442260822,
        "name": "Kyajori",
        "ele": "6151",
        "realCoord": {
            "lat": 27.9090478,
            "lon": 86.6697903
        },
        "group": 1699,
        "estimatedCoord": {
            "lat": 27.90872222222222,
            "lon": 86.67152777777775
        },
        "distance": 174.57928876392197
    },
    {
        "id": 477904058,
        "name": "Ama Dablam",
        "ele": "6856",
        "realCoord": {
            "lat": 27.8621001,
            "lon": 86.8604289
        },
        "group": 2126,
        "estimatedCoord": {
            "lat": 27.861706349206354,
            "lon": 86.8615476190476
        },
        "distance": 118.40762117308125
    },
    {
        "id": 565159946,
        "name": "मकालु 马卡鲁山 Makalu",
        "ele": "8485",
        "realCoord": {
            "lat": 27.8913935,
            "lon": 87.0886146
        },
        "group": 5086,
        "estimatedCoord": {
            "lat": 27.889852941176468,
            "lon": 87.08931372549019
        },
        "distance": 184.62619241402987
    },
    {
        "id": 996928321,
        "name": "Lhagoi Kangri",
        "ele": "5525",
        "realCoord": {
            "lat": 28.7913105,
            "lon": 87.6276511
        },
        "group": 8823,
        "estimatedCoord": {
            "lat": 28.79083333333334,
            "lon": 87.62662698412699
        },
        "distance": 113.06247487185207
    },
    {
        "id": 1326607409,
        "name": "South Peak",
        "ele": "8765",
        "realCoord": {
            "lat": 27.984918,
            "lon": 86.9253087
        },
        "group": 2283,
        "estimatedCoord": {
            "lat": 27.988333333333333,
            "lon": 86.92522357723577
        },
        "distance": 379.97895430392595
    },
    {
        "id": 1518744167,
        "name": "Parchemuche",
        "ele": "6279",
        "realCoord": {
            "lat": 27.8374114,
            "lon": 86.5471894
        },
        "group": 1376,
        "estimatedCoord": {
            "lat": 27.835833333333326,
            "lon": 86.54710144927536
        },
        "distance": 175.74113333963112
    },
    {
        "id": 1679250333,
        "name": "Chukhung Ri",
        "ele": "5546",
        "realCoord": {
            "lat": 27.9255663,
            "lon": 86.8789664
        },
        "group": 2171,
        "estimatedCoord": {
            "lat": 27.92558333333333,
            "lon": 86.8793333333333
        },
        "distance": 36.11115919597045
    },
    {
        "id": 2526429858,
        "name": "Cholatse",
        "ele": "6440",
        "realCoord": {
            "lat": 27.9190402,
            "lon": 86.7648644
        },
        "group": 1890,
        "estimatedCoord": {
            "lat": 27.919656862745104,
            "lon": 86.76605392156864
        },
        "distance": 135.54630213902968
    },
    {
        "id": 2526437540,
        "name": "Taboche",
        "ele": "6495",
        "realCoord": {
            "lat": 27.8973138,
            "lon": 86.7793702
        },
        "group": 1932,
        "estimatedCoord": {
            "lat": 27.897380952380953,
            "lon": 86.7795238095238
        },
        "distance": 16.846718028755923
    },
    {
        "id": 2677892526,
        "name": "章子峰Changtse",
        "ele": "7543",
        "realCoord": {
            "lat": 28.024329,
            "lon": 86.9151856
        },
        "group": 4707,
        "estimatedCoord": {
            "lat": 28.024907407407404,
            "lon": 86.91499999999999
        },
        "distance": 66.86734737087782
    },
    {
        "id": 2677892527,
        "name": "Cho Polu",
        "ele": "6735",
        "realCoord": {
            "lat": 27.9194539,
            "lon": 86.9819868
        },
        "group": 2433,
        "estimatedCoord": {
            "lat": 27.91942528735632,
            "lon": 86.98221264367815
        },
        "distance": 22.423693025261613
    },
    {
        "id": 2677892528,
        "name": "Khumbutse",
        "ele": "6636",
        "realCoord": {
            "lat": 28.0219052,
            "lon": 86.872193
        },
        "group": 4603,
        "estimatedCoord": {
            "lat": 28.021249999999995,
            "lon": 86.87275
        },
        "distance": 91.11747868602991
    },
    {
        "id": 2677892529,
        "name": "Lhotse Shar",
        "ele": "8382",
        "realCoord": {
            "lat": 27.9587111,
            "lon": 86.9437467
        },
        "group": 2332,
        "estimatedCoord": {
            "lat": 27.95833333333333,
            "lon": 86.94327777777777
        },
        "distance": 62.354565730262365
    },
    {
        "id": 2677892530,
        "name": "Lingtren",
        "ele": "7161",
        "realCoord": {
            "lat": 28.0278017,
            "lon": 86.8546651
        },
        "group": 4558,
        "estimatedCoord": {
            "lat": 28.028012820512817,
            "lon": 86.85472222222224
        },
        "distance": 24.143366250427892
    },
    {
        "id": 2677892532,
        "name": "Peak 38",
        "ele": "7590",
        "realCoord": {
            "lat": 27.9556165,
            "lon": 86.9646815
        },
        "group": 2386,
        "estimatedCoord": {
            "lat": 27.95557692307692,
            "lon": 86.965
        },
        "distance": 31.60092075463796
    },
    {
        "id": 2677892533,
        "name": "Pumori",
        "ele": "7161",
        "realCoord": {
            "lat": 28.0160417,
            "lon": 86.8273988
        },
        "group": 4490,
        "estimatedCoord": {
            "lat": 28.01587121212121,
            "lon": 86.82768939393938
        },
        "distance": 34.26158952887241
    },
    {
        "id": 2677892534,
        "name": "Shartse",
        "ele": "7457",
        "realCoord": {
            "lat": 27.9494404,
            "lon": 86.9829938
        },
        "group": 2436,
        "estimatedCoord": {
            "lat": 27.949509803921565,
            "lon": 86.98313725490196
        },
        "distance": 16.070881245729932
    },
    {
        "id": 2681940767,
        "name": "珠穆朗玛峰 - सगरमाथा",
        "ele": "8848",
        "realCoord": {
            "lat": 27.9879971,
            "lon": 86.9249654
        },
        "group": 2283,
        "estimatedCoord": {
            "lat": 27.988333333333333,
            "lon": 86.92522357723577
        },
        "distance": 45.18569383041767
    },
    {
        "id": 2683830785,
        "name": "Chumbu",
        "ele": "6859",
        "realCoord": {
            "lat": 28.0136395,
            "lon": 86.7878294
        },
        "group": 4385,
        "estimatedCoord": {
            "lat": 28.013482905982908,
            "lon": 86.78848290598293
        },
        "distance": 66.49462167609869
    },
    {
        "id": 2683857479,
        "name": "Lobuche",
        "ele": "6145",
        "realCoord": {
            "lat": 27.9691317,
            "lon": 86.7816135
        },
        "group": 1940,
        "estimatedCoord": {
            "lat": 27.969484126984124,
            "lon": 86.78218253968255
        },
        "distance": 68.27615356032159
    },
    {
        "id": 2685954298,
        "name": "Baruntse",
        "ele": "7075",
        "realCoord": {
            "lat": 27.8720615,
            "lon": 86.9796489
        },
        "group": 2428,
        "estimatedCoord": {
            "lat": 27.87203703703704,
            "lon": 86.97984567901234
        },
        "distance": 19.538980644536558
    },
    {
        "id": 2686511084,
        "name": "Gauri Sankar",
        "ele": "7134",
        "realCoord": {
            "lat": 27.967351,
            "lon": 86.3345048
        },
        "group": 759,
        "estimatedCoord": {
            "lat": 27.96578431372549,
            "lon": 86.33497549019607
        },
        "distance": 180.29295895970455
    },
    {
        "id": 2686686024,
        "name": "Hungchi",
        "ele": "7036",
        "realCoord": {
            "lat": 28.0346849,
            "lon": 86.7597051
        },
        "group": 4309,
        "estimatedCoord": {
            "lat": 28.034380341880343,
            "lon": 86.75946581196582
        },
        "distance": 41.22498675532209
    },
    {
        "id": 2687648807,
        "name": "Lhotse Nup",
        "ele": "8410",
        "realCoord": {
            "lat": 27.9614022,
            "lon": 86.9309715
        },
        "group": 2308,
        "estimatedCoord": {
            "lat": 27.96193333333333,
            "lon": 86.93353333333333
        },
        "distance": 258.5280164613276
    },
    {
        "id": 2689043822,
        "name": "Ngozumpa Kang I",
        "ele": "7916",
        "realCoord": {
            "lat": 28.1068465,
            "lon": 86.6850856
        },
        "group": 4098,
        "estimatedCoord": {
            "lat": 28.106315789473683,
            "lon": 86.68469298245616
        },
        "distance": 70.48753917385545
    },
    {
        "id": 2689043824,
        "name": "Ngozumpa Kang II",
        "ele": "7743",
        "realCoord": {
            "lat": 28.1058708,
            "lon": 86.7054038
        },
        "group": 4148,
        "estimatedCoord": {
            "lat": 28.106447368421048,
            "lon": 86.70561403508772
        },
        "distance": 67.3671259307809
    },
    {
        "id": 2689711574,
        "name": "Ngozumpa Tse",
        "ele": "5553",
        "realCoord": {
            "lat": 28.0177777,
            "lon": 86.6838749
        },
        "group": 4096,
        "estimatedCoord": {
            "lat": 28.017291666666665,
            "lon": 86.68424999999999
        },
        "distance": 65.41618595980927
    },
    {
        "id": 2689806446,
        "name": "Mera Peak",
        "ele": "6476",
        "realCoord": {
            "lat": 27.7098398,
            "lon": 86.8686622
        },
        "group": 2145,
        "estimatedCoord": {
            "lat": 27.7094696969697,
            "lon": 86.86818181818182
        },
        "distance": 62.70909710585489
    },
    {
        "id": 2881473816,
        "name": "Kartse",
        "realCoord": {
            "lat": 28.0328718,
            "lon": 87.0042152
        },
        "group": 7102,
        "estimatedCoord": {
            "lat": 28.032434210526315,
            "lon": 87.00405701754384
        },
        "distance": 51.090653512879406
    },
    {
        "id": 2881620364,
        "name": "Chamlang",
        "ele": "7319",
        "realCoord": {
            "lat": 27.7772801,
            "lon": 86.98151
        },
        "group": 2430,
        "estimatedCoord": {
            "lat": 27.77502688172043,
            "lon": 86.98032258064515
        },
        "distance": 276.5297769450227
    },
    {
        "id": 2902740258,
        "name": "Naulekh",
        "ele": "6363",
        "realCoord": {
            "lat": 27.6875828,
            "lon": 86.9024898
        },
        "group": 2227,
        "estimatedCoord": {
            "lat": 27.687767857142855,
            "lon": 86.90282738095237
        },
        "distance": 39.105277797117054
    },
    {
        "id": 2904495697,
        "name": "Kangchungtse",
        "ele": "7678",
        "realCoord": {
            "lat": 27.9140498,
            "lon": 87.0804271
        },
        "group": 5067,
        "estimatedCoord": {
            "lat": 27.914666666666665,
            "lon": 87.07922222222221
        },
        "distance": 136.8662894669779
    },
    {
        "id": 2904495698,
        "name": "Makalu Southeast",
        "ele": "7860",
        "realCoord": {
            "lat": 27.8791784,
            "lon": 87.0995612
        },
        "group": 5103,
        "estimatedCoord": {
            "lat": 27.879222222222225,
            "lon": 87.097
        },
        "distance": 251.86433378444778
    },
    {
        "id": 2904495699,
        "name": "Pethangtse",
        "ele": "6738",
        "realCoord": {
            "lat": 27.957236,
            "lon": 87.0152042
        },
        "group": 4947,
        "estimatedCoord": {
            "lat": 27.95729166666667,
            "lon": 87.01555555555555
        },
        "distance": 35.071248943529326
    },
    {
        "id": 2904629928,
        "name": "珠穆隆索峰",
        "ele": "7804",
        "realCoord": {
            "lat": 27.9300846,
            "lon": 87.1075096
        },
        "group": 5121,
        "estimatedCoord": {
            "lat": 27.93029411764706,
            "lon": 87.10757352941178
        },
        "distance": 24.136606353577672
    },
    {
        "id": 2906971419,
        "name": "Numbur",
        "ele": "6959",
        "realCoord": {
            "lat": 27.7542227,
            "lon": 86.572647
        },
        "group": 1457,
        "estimatedCoord": {
            "lat": 27.754404761904755,
            "lon": 86.57383928571426
        },
        "distance": 119.09474296176685
    },
    {
        "id": 2908665203,
        "name": "乔格茹峰",
        "ele": "7181",
        "realCoord": {
            "lat": 27.9720795,
            "lon": 86.4330115
        },
        "group": 1021,
        "estimatedCoord": {
            "lat": 27.971750000000004,
            "lon": 86.43261111111111
        },
        "distance": 53.761357103411434
    },
    {
        "id": 2950781582,
        "name": "Pokalde",
        "ele": "5806",
        "realCoord": {
            "lat": 27.9247682,
            "lon": 86.8331902
        },
        "group": 2045,
        "estimatedCoord": {
            "lat": 27.924960317460318,
            "lon": 86.83345238095237
        },
        "distance": 33.474885481733786
    },
    {
        "id": 3120550378,
        "name": "Nangpa Og",
        "ele": "4569",
        "realCoord": {
            "lat": 27.7309459,
            "lon": 86.4741821
        },
        "group": 1144,
        "estimatedCoord": {
            "lat": 27.730833333333333,
            "lon": 86.47416666666666
        },
        "distance": 12.612633894587661
    },
    {
        "id": 3120550379,
        "name": "Nangpa Teng",
        "ele": "4629",
        "realCoord": {
            "lat": 27.7352038,
            "lon": 86.473303
        },
        "group": 1137,
        "estimatedCoord": {
            "lat": 27.734385964912278,
            "lon": 86.4740789473684
        },
        "distance": 118.78950609449835
    },
    {
        "id": 3134662214,
        "name": "Baramji",
        "ele": "4182",
        "realCoord": {
            "lat": 27.7329336,
            "lon": 86.3278995
        },
        "group": 745,
        "estimatedCoord": {
            "lat": 27.730753968253975,
            "lon": 86.32712301587303
        },
        "distance": 254.20742496856352
    },
    {
        "id": 3213654115,
        "name": "PT 6465",
        "ele": "6465",
        "realCoord": {
            "lat": 27.7340748,
            "lon": 86.6112098
        },
        "group": 1546,
        "estimatedCoord": {
            "lat": 27.733297101449274,
            "lon": 86.61210144927536
        },
        "distance": 123.2433648675817
    },
    {
        "id": 3696097628,
        "name": "Nuptse I",
        "ele": "7861",
        "realCoord": {
            "lat": 27.9679586,
            "lon": 86.887081
        },
        "group": 2188,
        "estimatedCoord": {
            "lat": 27.96718253968254,
            "lon": 86.88746031746031
        },
        "distance": 94.0209138161683
    },
    {
        "id": 3696097629,
        "name": "Nuptse II",
        "ele": "7827",
        "realCoord": {
            "lat": 27.9658595,
            "lon": 86.8903249
        },
        "group": 2188,
        "estimatedCoord": {
            "lat": 27.96718253968254,
            "lon": 86.88746031746031
        },
        "distance": 317.5732688193662
    },
    {
        "id": 3696097631,
        "name": "Nuptse Nup II",
        "ele": "7742",
        "realCoord": {
            "lat": 27.9695763,
            "lon": 86.8820341
        },
        "group": 2177,
        "estimatedCoord": {
            "lat": 27.96861111111111,
            "lon": 86.88291666666666
        },
        "distance": 137.9960239399521
    },
    {
        "id": 3696097633,
        "name": "Nuptse Shar II",
        "ele": "7776",
        "realCoord": {
            "lat": 27.9625362,
            "lon": 86.8957145
        },
        "group": 2210,
        "estimatedCoord": {
            "lat": 27.961666666666666,
            "lon": 86.89453703703704
        },
        "distance": 150.78497304437153
    },
    {
        "id": 3696097634,
        "name": "Nuptse Shar III",
        "ele": "7695",
        "realCoord": {
            "lat": 27.9613655,
            "lon": 86.8985403
        },
        "group": 2221,
        "estimatedCoord": {
            "lat": 27.96041666666667,
            "lon": 86.89861111111112
        },
        "distance": 105.76761694644793
    },
    {
        "id": 3761207074,
        "name": "Colangma",
        "ele": "6952",
        "realCoord": {
            "lat": 28.316462,
            "lon": 86.2858861
        },
        "group": 3218,
        "estimatedCoord": {
            "lat": 28.31675213675214,
            "lon": 86.28480769230768
        },
        "distance": 110.41900739942815
    },
    {
        "id": 3761207075,
        "name": "Lapche Kang I",
        "ele": "7367",
        "realCoord": {
            "lat": 28.3044064,
            "lon": 86.3511931
        },
        "group": 3369,
        "estimatedCoord": {
            "lat": 28.303611111111106,
            "lon": 86.3506818181818
        },
        "distance": 101.64751759331214
    },
    {
        "id": 3761207076,
        "name": "Lapche Kang II",
        "ele": "7072",
        "realCoord": {
            "lat": 28.3046025,
            "lon": 86.3220117
        },
        "group": 3294,
        "estimatedCoord": {
            "lat": 28.30435416666667,
            "lon": 86.32097916666666
        },
        "distance": 104.82212837955265
    },
    {
        "id": 3761207077,
        "name": "Lapche Kang III West",
        "ele": "7020",
        "realCoord": {
            "lat": 28.307943,
            "lon": 86.3757696
        },
        "group": 3417,
        "estimatedCoord": {
            "lat": 28.30805555555556,
            "lon": 86.375625
        },
        "distance": 18.901199094391718
    },
    {
        "id": 3761207078,
        "name": "Lapche Kang III",
        "ele": "7250",
        "realCoord": {
            "lat": 28.3019881,
            "lon": 86.3845306
        },
        "group": 3427,
        "estimatedCoord": {
            "lat": 28.30143518518519,
            "lon": 86.38384259259261
        },
        "distance": 91.22652044870573
    },
    {
        "id": 4011190127,
        "name": "正江岗日",
        "realCoord": {
            "lat": 28.7010582,
            "lon": 87.911662
        },
        "group": 9294,
        "estimatedCoord": {
            "lat": 28.70071705426357,
            "lon": 87.9118023255814
        },
        "distance": 40.339846626419224
    },
    {
        "id": 4079548654,
        "name": "觉木桑珠玛",
        "realCoord": {
            "lat": 28.0912615,
            "lon": 86.8122881
        },
        "group": 4451,
        "estimatedCoord": {
            "lat": 28.089285714285722,
            "lon": 86.81309523809526
        },
        "distance": 233.60284277101673
    },
    {
        "id": 4079817699,
        "name": "Nangpai Gosum",
        "ele": "7350",
        "realCoord": {
            "lat": 28.0729512,
            "lon": 86.6124231
        },
        "group": 3968,
        "estimatedCoord": {
            "lat": 28.073530701754382,
            "lon": 86.61401315789473
        },
        "distance": 168.84168188784284
    },
    {
        "id": 4079817701,
        "name": "Siguang Ri",
        "ele": "7308",
        "realCoord": {
            "lat": 28.1478873,
            "lon": 86.684561
        },
        "group": 4100,
        "estimatedCoord": {
            "lat": 28.14757575757576,
            "lon": 86.68537878787879
        },
        "distance": 87.37050777146307
    },
    {
        "id": 4526922890,
        "name": "Tsoboje",
        "ele": "6689",
        "realCoord": {
            "lat": 27.8745166,
            "lon": 86.5089226
        },
        "group": 1255,
        "estimatedCoord": {
            "lat": 27.875370370370373,
            "lon": 86.50935185185186
        },
        "distance": 103.92122948771402
    },
    {
        "id": 4919102857,
        "name": "Sunder Peak",
        "ele": "5300",
        "realCoord": {
            "lat": 27.8395099,
            "lon": 86.6143533
        },
        "group": 1555,
        "estimatedCoord": {
            "lat": 27.839596774193545,
            "lon": 86.61521505376342
        },
        "distance": 85.30766025996097
    }
]